wkd/__init__.py
wkd/__main__.py
wkd/options.py
wkd/parser.py
wkd/utils.py
wkd/which.py
wkd-0.0.2.dist-info/LICENSE
wkd-0.0.2.dist-info/METADATA
wkd-0.0.2.dist-info/WHEEL
wkd-0.0.2.dist-info/entry_points.txt
wkd-0.0.2.dist-info/top_level.txt
wkd-0.0.2.dist-info/RECORD
