Metadata-Version: 2.1
Name: wkd
Version: 0.0.2
Summary: Which key via dmenu.
License: GNU General Public License v3 (GPLv3)
Project-URL: repository, https://codeberg.org/johndovern/wdk
Keywords: dmenu
License-File: LICENSE
Requires-Dist: loadconf
Requires-Dist: promptx
